quip/__init__.py
quip/cli.py
quip/external.py
quip/fact.py
quip/field_builder.py
quip/quip.py
quip/version_builder.py
quip/services/__init__.py
quip/services/config_service.py
quip/services/external_service.py
quip/services/fields_service.py
quip/services/generator_service.py
quip/services/icons_service.py
quip/services/project_service.py
quip/services/qsa_parser.py
quip/services/template_service.py
quip/services/uip_service.py
quip/services/version_service.py
tests/__init__.py
tests/conftest.py
tests/test_field_builder.py
tests/test_integration.py
tests/test_quip_class.py
tests/test_utils.py
tests/test_version_builder.py
quip_cli-2.0.0.dist-info/METADATA
quip_cli-2.0.0.dist-info/WHEEL
quip_cli-2.0.0.dist-info/entry_points.txt
quip_cli-2.0.0.dist-info/top_level.txt
quip_cli-2.0.0.dist-info/RECORD
