Metadata-Version: 2.1
Name: quip-cli
Version: 2.0.0
Summary: Tool for creating/updating new universal integrations
Author: Stonebranch
Author-email: huseyin.gomleksizoglu@stonebranch.com
Classifier: Operating System :: POSIX :: Linux
Classifier: Operating System :: Microsoft :: Windows
Classifier: Programming Language :: Python :: 3
Requires-Python: >=3.7
Requires-Dist: colorama (>=0.4.4)
Requires-Dist: setuptools (>=44.1.1)
Requires-Dist: Pillow
Requires-Dist: uip-cli (>=1.3.0)
Requires-Dist: pyyaml
Requires-Dist: python-gitlab
Requires-Dist: python-jenkins
Requires-Dist: keyring
Requires-Dist: click (>=8.0.0)
